{
  "Chen Lin": {
    "Nickname": " 大头 (DaTou), Lynn",
    "Birthday": " 1998-07-23",
    "Age": " 21 Years Old",
    "Constellation": " 狮子座 (Leo)",
    "Birthplace": " 上海, 中国 (Shanghai, China)",
    "Height": " 165 cm",
    "PersonalSpecialties": " 唱歌 (Singing)、日语 (Japanese)",
    "Hobbies": " 运动 (Sports)、看动漫 (Watching Anime)、看小说 (Reading Novels)",
    "MemberWeibo": " "
  },
  "Feng XiaoFei": {
    "Nickname": " 灰灰 (HuiHui)",
    "Birthday": " 1995-10-17",
    "Age": " 24 Years Old",
    "Constellation": " 天秤座 (Libra)",
    "Birthplace": " 河南, 中国 (Henan, China)",
    "Height": " 160 cm",
    "PersonalSpecialties": " 舞蹈 (Dance)、绕口令 (Tongue Twister)",
    "Hobbies": " 偶像研究 (Idol Research)",
    "MemberWeibo": " "
  },
  "Li XingYu": {
    "Nickname": " 抛抛 (PaoPao)",
    "Birthday": " 2000-02-06",
    "Age": " 20 Years Old",
    "Constellation": " 水瓶座 (Aquarius)",
    "Birthplace": " 上海, 中国 (Shanghai, China)",
    "Height": " 163 cm",
    "PersonalSpecialties": " 朗诵 (Recite)",
    "Hobbies": " 看书 (Reading)、主持 (Hosting)",
    "MemberWeibo": " "
  },
  "Li Zhao": {
    "Nickname": " 桃子 (TaoZi)",
    "Birthday": " 1997-05-23",
    "Age": " 23 Years Old",
    "Constellation": " 双子座 (Gemini)",
    "Birthplace": " 湖南, 中国 (Hunan, China)",
    "Height": " 165 cm",
    "PersonalSpecialties": " 数独 (Sudoku)",
    "Hobbies": " 日剧 (Japanese Drama)、听歌 (Listening To Songs)、动漫 (Anime)",
    "MemberWeibo": " "
  },
  "Lv Yi": {
    "Nickname": " 口口一 (KouKouYi)",
    "Birthday": " 1997-06-27",
    "Age": " 23 Years Old",
    "Constellation": " 巨蟹座 (Cancer)",
    "Birthplace": " 重庆, 中国 (Chongqing, China)",
    "Height": " 164 cm",
    "PersonalSpecialties": " 舞蹈 (Dance)、劈叉跳 (Split Jump)、颜艺 (YanYi)、反射弧 (Reflex Arc)",
    "Hobbies": " 模仿 (Imitation)、自言自语 (Self-Talk)、观察人类 (Observation Of Human Beings)、wota艺 (Wota Art)",
    "MemberWeibo": " "
  },
  "Pan LuYao": {
    "Nickname": " 鹿儿 (LuEr)、小鹿 (Small Deer)",
    "Birthday": " ????-07-10",
    "Age": " ?? Years Old",
    "Constellation": " 巨蟹座 (Cancer)",
    "Birthplace": " 上海, 中国 (Shanghai, China)",
    "Height": " 165 cm",
    "PersonalSpecialties": " 配音 (Dubbing)、古筝 (Guzheng)",
    "Hobbies": " 手账 (Diary)、摄影 (Photography)",
    "MemberWeibo": " "
  },
  "Pan YingQi": {
    "Nickname": " 羽羽 (YuYu)",
    "Birthday": " 1998-09-27",
    "Age": " 21 Years Old",
    "Constellation": " 天秤座 (Libra)",
    "Birthplace": " 上海, 中国 (Shanghai, China)",
    "Height": " 164 cm",
    "PersonalSpecialties": " 日语 (Japanese)、唱歌 (Singing)、擅长脑补 (Good At Brain Mending)、短跑 (Sprint)、立定跳远 (Standing Long Jump)、耐力 (Endurance)",
    "Hobbies": " 看游戏 (Watch Games)、打游戏 (Play Games)、动漫 (Anime)、舞蹈 (Dance)、唱歌 (Singing)、脑补 (Brain Mending)、ACG、宅舞 (ZhaiWu)",
    "MemberWeibo": " "
  },
  "Qi Jing": {
    "Nickname": " 静静 (JingJing)",
    "Birthday": " 1998-07-19",
    "Age": " 21 Years Old",
    "Constellation": " 巨蟹座 (Cancer)",
    "Birthplace": " 上海, 中国 (Shanghai, China)",
    "Height": " 160 cm",
    "PersonalSpecialties": " 舞蹈 (Dance)",
    "Hobbies": " 唱歌 (Singing)、跳舞 (Dancing)、表演 (Acting)",
    "MemberWeibo": " "
  },
  "Ran Wei": {
    "Nickname": " 软软 (RuanRuan)",
    "Birthday": " 1999-05-21",
    "Age": " 21 Years Old",
    "Constellation": " 双子座 (Gemini)",
    "Birthplace": " 四川, 中国 (Sichuan, China)",
    "Height": " 160 cm",
    "PersonalSpecialties": " 抓娃娃、吃",
    "Hobbies": " ACG、吃、躺着",
    "MemberWeibo": " "
  },
  "Song XinRan": {
    "Nickname": " 冉冉 (RanRan)",
    "Birthday": " 1997-07-08",
    "Age": " 23 Years Old",
    "Constellation": " 巨蟹座 (Cancer)",
    "Birthplace": " 山东, 中国 (Shandong, China)",
    "Height": " 166 cm",
    "PersonalSpecialties": " 唱歌 (Singing)、拉丁舞 (Latin Dance)、二胡 (ErHu)",
    "Hobbies": " 运动 (Sports)、旅游 (Travel)、看电影 (Watching Movies)",
    "MemberWeibo": " "
  },
  "Sun XinWen": {
    "Nickname": " 新闻 (Xin Wen/News)",
    "Birthday": " 1994-11-04",
    "Age": " 25 Years Old",
    "Constellation": " 天蝎座 (Scorpio)",
    "Birthplace": " 上海, 中国 (Shanghai, China)",
    "Height": " 170 cm",
    "PersonalSpecialties": " 唱歌 (Singing)、音频制作 (Audio Production)",
    "Hobbies": " 吃巧克力 (Eating Chocolate)、录歌 (Recording Songs)、单机游戏 (PC Games)",
    "MemberWeibo": " "
  },
  "Wang FeiYan": {
    "Nickname": " 七七 (QiQi)",
    "Birthday": " ????-01-27",
    "Age": " ?? Years Old",
    "Constellation": " 水瓶座 (Aquarius)",
    "Birthplace": " 辽宁, 中国 (Liaoning, China)",
    "Height": " 166 cm",
    "PersonalSpecialties": " 国标舞、民族舞、手工创作",
    "Hobbies": " 舞蹈、表演、摄影、调色",
    "MemberWeibo": " "
  },
  "Wang JiaLing": {
    "Nickname": " 九九 (JiuJiu)",
    "Birthday": " 1999-07-13",
    "Age": " 21 Years Old",
    "Constellation": " 巨蟹座 (Cancer)",
    "Birthplace": " 福建, 中国 (Fujian, China)",
    "Height": " 172 cm",
    "PersonalSpecialties": " 爵士舞 (Jazz Dance)、手工 (Handicraft)",
    "Hobbies": " 看美剧 (Watch American Drama)、动漫 (Anime)、美食 (Gourmet Food)",
    "MemberWeibo": " "
  },
  "Wang RuiQi": {
    "Nickname": " 睿琦 (RuiQi)",
    "Birthday": " 1999-12-15",
    "Age": " 20 Years Old",
    "Constellation": " 射手座 (Sagittarius)",
    "Birthplace": " 内蒙古, 中国 (Inner Mongolia, China)",
    "Height": " 165 cm",
    "PersonalSpecialties": " 唱歌 (Singing)、跳舞 (Dancing)、画画 (Drawing)",
    "Hobbies": " 尤克里里 (Ukelele)、电子琴 (Electric Guitar)",
    "MemberWeibo": " "
  },
  "Wang XiaoJia": {
    "Nickname": " 天草 (TianCao)",
    "Birthday": " 1993-05-31",
    "Age": " 27 Years Old",
    "Constellation": " 双子座 (Gemini)",
    "Birthplace": " 湖南, 中国 (Hunan, China)",
    "Height": " 170 cm",
    "PersonalSpecialties": " 宅舞 (ZhaiWu)、主持 (Host)",
    "Hobbies": " 游戏 (Game)、动漫 (Anime)、游戏实况解说 (Game Live Commentary)",
    "MemberWeibo": " "
  },
  "Xie TianYi": {
    "Nickname": " 笨笨 (BenBen)",
    "Birthday": " 1998-06-24",
    "Age": " 22 Years Old",
    "Constellation": " 巨蟹座 (Cancer)",
    "Birthplace": " 北京, 中国 (Beijing, China)",
    "Height": " 168 cm",
    "PersonalSpecialties": " 击剑 (Fencing)",
    "Hobbies": " 看搞笑视频 (Watch Funny Videos)、看电影 (Watch Movies)、旅游 (Travel)",
    "MemberWeibo": " "
  },
  "Yang BingYi": {
    "Nickname": " 水水 (ShuiShui), 二水 (ErShui)",
    "Birthday": " 2000-07-26",
    "Age": " 19 Years Old",
    "Constellation": " 狮子座 (Leo)",
    "Birthplace": " 海南, 中国 (Hainan, China)",
    "Height": " 165 cm",
    "PersonalSpecialties": " 舞蹈 (Dance)、体育 (Sports)",
    "Hobbies": " 追番 (Chasing Japanese Anime)、宅舞 (ZhaiWu)、恐怖片 (Horror Film)、Cosplay",
    "MemberWeibo": " "
  },
  "Zhang JiaYu": {
    "Nickname": " 沐沐 (MuMu)",
    "Birthday": " 2001-06-15",
    "Age": " 19 Years Old",
    "Constellation": " 双子座 (Gemini)",
    "Birthplace": " 浙江, 中国 (Zhejiang, China)",
    "Height": " 169 cm",
    "PersonalSpecialties": " 唱歌 (Singing)、古筝 (Guzheng)、平面拍摄 (Advertisement Shooting)",
    "Hobbies": " Lolita、动漫 (Anime)、LOL、做各种好吃的 (Do All Kinds of Delicious Food)",
    "MemberWeibo": " "
  },
  "Zhang QiongYu": {
    "Nickname": " Soso",
    "Birthday": " 1997-01-21",
    "Age": " 23 Years Old",
    "Constellation": " 水瓶座 (Aquarius)",
    "Birthplace": " 浙江, 中国 (Zhejiang, China)",
    "Height": " 163 cm",
    "PersonalSpecialties": " 跳舞 (Dancing)",
    "Hobbies": " 游泳 (Swimming)、追日剧 (Chasing Japanese Dramas)、宅舞 (ZhaiWu)",
    "MemberWeibo": " "
  }
}
